LbMessagingAdministration
